Workbook

Sheet Sales_Transactions
A1: Transaction_ID | B1: Date | C1: Store_ID | D1: Salon_Location | E1: Brand | F1: Product_ID | G1: Product_Name | H1: Category | I1: Stylist | J1: Units_Sold | K1: Unit_Cost | L1: Retail_Price | M1: Discount_% | N1: Net_Sales | O1: COGS | P1: Gross_Profit | Q1: Gross_Margin_% | R1: Payment_Method | S1: Customer_Type
A2: TRX-0001 | B2: 46093 | C2: CG-001 | D2: Gabriel Samra Coral Gables | E2: Truss | F2: TRU-CND-002 | G2: Infusion Conditioner | H2: Hair Care | I2: Magaly | J2: 1 | K2: 15.25 | L2: 34 | M2: 0 | N2: =J2*L2*(1-M2) -> 34 | O2: =J2*K2 -> 15.25 | P2: =N2-O2 -> 18.75 | Q2: =IF(N2=0,0,P2/N2) -> 0.55147059 | R2: Card | S2: Stylist Recommendation
A3: TRX-0002 | B3: 46046 | C3: CG-001 | D3: Gabriel Samra Coral Gables | E3: Truss | F3: TRU-SHP-001 | G3: Infusion Shampoo | H3: Hair Care | I3: Melia | J3: 1 | K3: 14.5 | L3: 32 | M3: 0 | N3: =J3*L3*(1-M3) -> 32 | O3: =J3*K3 -> 14.5 | P3: =N3-O3 -> 17.5 | Q3: =IF(N3=0,0,P3/N3) -> 0.546875 | R3: Cash | S3: Stylist Recommendation
A4: TRX-0003 | B4: 46094 | C4: DR-001 | D4: Gabriel Samra Doral | E4: Truss | F4: TRU-OIL-004 | G4: Deluxe Prime Oil | H4: Finishing | I4: Isaac | J4: 2 | K4: 18 | L4: 42 | M4: 0 | N4: =J4*L4*(1-M4) -> 84 | O4: =J4*K4 -> 36 | P4: =N4-O4 -> 48 | Q4: =IF(N4=0,0,P4/N4) -> 0.57142857 | R4: Gift Card | S4: Post-Service Retail
A5: TRX-0004 | B5: 46078 | C5: CG-001 | D5: Gabriel Samra Coral Gables | E5: Truss | F5: TRU-SER-005 | G5: Night Spa Serum | H5: Treatment | I5: Magaly | J5: 3 | K5: 19.75 | L5: 48 | M5: 0 | N5: =J5*L5*(1-M5) -> 144 | O5: =J5*K5 -> 59.25 | P5: =N5-O5 -> 84.75 | Q5: =IF(N5=0,0,P5/N5) -> 0.58854167 | R5: Gift Card | S5: Existing Client
A6: TRX-0005 | B6: 46090 | C6: DR-001 | D6: Gabriel Samra Doral | E6: Sutra | F6: SUT-FIR-001 | G6: Mini Flat Iron | H6: Hot Tools | I6: Magaly | J6: 2 | K6: 38 | L6: 89 | M6: 0.05 | N6: =J6*L6*(1-M6) -> 169.1 | O6: =J6*K6 -> 76 | P6: =N6-O6 -> 93.1 | Q6: =IF(N6=0,0,P6/N6) -> 0.5505618 | R6: Gift Card | S6: Existing Client
A7: TRX-0006 | B7: 46115 | C7: DR-001 | D7: Gabriel Samra Doral | E7: Sutra | F7: SUT-DRY-004 | G7: Professional Hair Dryer | H7: Hot Tools | I7: Melia | J7: 1 | K7: 62 | L7: 149 | M7: 0.05 | N7: =J7*L7*(1-M7) -> 141.55 | O7: =J7*K7 -> 62 | P7: =N7-O7 -> 79.55 | Q7: =IF(N7=0,0,P7/N7) -> 0.56199223 | R7: Cash | S7: Post-Service Retail
A8: TRX-0007 | B8: 46048 | C8: CG-001 | D8: Gabriel Samra Coral Gables | E8: Truss | F8: TRU-CND-002 | G8: Infusion Conditioner | H8: Hair Care | I8: Melia | J8: 1 | K8: 15.25 | L8: 34 | M8: 0 | N8: =J8*L8*(1-M8) -> 34 | O8: =J8*K8 -> 15.25 | P8: =N8-O8 -> 18.75 | Q8: =IF(N8=0,0,P8/N8) -> 0.55147059 | R8: Cash | S8: Post-Service Retail
A9: TRX-0008 | B9: 46091 | C9: CG-001 | D9: Gabriel Samra Coral Gables | E9: Sutra | F9: SUT-FIR-001 | G9: Mini Flat Iron | H9: Hot Tools | I9: Magaly | J9: 1 | K9: 38 | L9: 89 | M9: 0.05 | N9: =J9*L9*(1-M9) -> 84.55 | O9: =J9*K9 -> 38 | P9: =N9-O9 -> 46.55 | Q9: =IF(N9=0,0,P9/N9) -> 0.5505618 | R9: Cash | S9: Walk-in Client
A10: TRX-0009 | B10: 46120 | C10: DR-001 | D10: Gabriel Samra Doral | E10: Truss | F10: TRU-MSK-003 | G10: Net Mask | H10: Treatment | I10: Isaac | J10: 1 | K10: 20 | L10: 45 | M10: 0.1 | N10: =J10*L10*(1-M10) -> 40.5 | O10: =J10*K10 -> 20 | P10: =N10-O10 -> 20.5 | Q10: =IF(N10=0,0,P10/N10) -> 0.50617284 | R10: Apple Pay | S10: Existing Client
A11: TRX-0010 | B11: 46103 | C11: CG-001 | D11: Gabriel Samra Coral Gables | E11: Truss | F11: TRU-OIL-004 | G11: Deluxe Prime Oil | H11: Finishing | I11: Melia | J11: 1 | K11: 18 | L11: 42 | M11: 0 | N11: =J11*L11*(1-M11) -> 42 | O11: =J11*K11 -> 18 | P11: =N11-O11 -> 24 | Q11: =IF(N11=0,0,P11/N11) -> 0.57142857 | R11: Cash | S11: Stylist Recommendation
A12: TRX-0011 | B12: 46059 | C12: DR-001 | D12: Gabriel Samra Doral | E12: Sutra | F12: SUT-CUR-002 | G12: Clipless Curling Iron | H12: Hot Tools | I12: Isaac | J12: 1 | K12: 42 | L12: 99 | M12: 0 | N12: =J12*L12*(1-M12) -> 99 | O12: =J12*K12 -> 42 | P12: =N12-O12 -> 57 | Q12: =IF(N12=0,0,P12/N12) -> 0.57575758 | R12: Gift Card | S12: Stylist Recommendation
A13: TRX-0012 | B13: 46058 | C13: CG-001 | D13: Gabriel Samra Coral Gables | E13: Sutra | F13: SUT-FIR-001 | G13: Mini Flat Iron | H13: Hot Tools | I13: Melia | J13: 1 | K13: 38 | L13: 89 | M13: 0 | N13: =J13*L13*(1-M13) -> 89 | O13: =J13*K13 -> 38 | P13: =N13-O13 -> 51 | Q13: =IF(N13=0,0,P13/N13) -> 0.57303371 | R13: Card | S13: Walk-in Client
... A151: TRX-0150 | B151: 46036 | C151: CG-001 | D151: Gabriel Samra Coral Gables | E151: Sutra | F151: SUT-HSP-005 | G151: Heat Spray | H151: Styling | I151: Melia | J151: 1 | K151: 9.5 | L151: 24 | M151: 0.05 | N151: =J151*L151*(1-M151) -> 22.8 | O151: =J151*K151 -> 9.5 | P151: =N151-O151 -> 13.3 | Q151: =IF(N151=0,0,P151/N151) -> 0.58333333 | R151: Card | S151: Post-Service Retail

Sheet Products
A1: Product_ID | B1: Brand | C1: Product_Name | D1: Category | E1: Size | F1: Unit_Cost | G1: Retail_Price | H1: Supplier | I1: Active
A2: TRU-SHP-001 | B2: Truss | C2: Infusion Shampoo | D2: Hair Care | E2: 300 ml | F2: 14.5 | G2: 32 | H2: Truss Professional | I2: Yes
A3: TRU-CND-002 | B3: Truss | C3: Infusion Conditioner | D3: Hair Care | E3: 300 ml | F3: 15.25 | G3: 34 | H3: Truss Professional | I3: Yes
A4: TRU-MSK-003 | B4: Truss | C4: Net Mask | D4: Treatment | E4: 180 g | F4: 20 | G4: 45 | H4: Truss Professional | I4: Yes
A5: TRU-OIL-004 | B5: Truss | C5: Deluxe Prime Oil | D5: Finishing | E5: 60 ml | F5: 18 | G5: 42 | H5: Truss Professional | I5: Yes
A6: TRU-SER-005 | B6: Truss | C6: Night Spa Serum | D6: Treatment | E6: 250 ml | F6: 19.75 | G6: 48 | H6: Truss Professional | I6: Yes
A7: SUT-FIR-001 | B7: Sutra | C7: Mini Flat Iron | D7: Hot Tools | E7: 1 inch | F7: 38 | G7: 89 | H7: Sutra Beauty | I7: Yes
A8: SUT-CUR-002 | B8: Sutra | C8: Clipless Curling Iron | D8: Hot Tools | E8: 1.25 inch | F8: 42 | G8: 99 | H8: Sutra Beauty | I8: Yes
A9: SUT-BLO-003 | B9: Sutra | C9: Blowout Brush | D9: Hot Tools | E9: One Size | F9: 48 | G9: 119 | H9: Sutra Beauty | I9: Yes
A10: SUT-DRY-004 | B10: Sutra | C10: Professional Hair Dryer | D10: Hot Tools | E10: 1875W | F10: 62 | G10: 149 | H10: Sutra Beauty | I10: Yes
A11: SUT-HSP-005 | B11: Sutra | C11: Heat Spray | D11: Styling | E11: 150 ml | F11: 9.5 | G11: 24 | H11: Sutra Beauty | I11: Yes

Sheet Inventory
A1: Inventory_ID | B1: Store_ID | C1: Salon_Location | D1: Brand | E1: Product_ID | F1: Product_Name | G1: Category | H1: Opening_Stock | I1: Units_Received | J1: Units_Sold | K1: Current_Stock | L1: Reorder_Point | M1: Recommended_Reorder_Qty | N1: Stock_Status | O1: Last_Received_Date
A2: INV-CG-001-TRU-SHP-001 | B2: CG-001 | C2: Gabriel Samra Coral Gables | D2: Truss | E2: TRU-SHP-001 | F2: Infusion Shampoo | G2: Hair Care | H2: 24 | I2: 26 | J2: =SUMIFS(Sales_Transactions!$J:$J,Sales_Transactions!$C:$C,B2,Sales_Transactions!$F:$F,E2) -> 9 | K2: =H2+I2-J2 -> 41 | L2: 8 | M2: 20 | N2: =IF(K2<=L2,"Reorder Needed",IF(K2<=L2*1.5,"Watch","Healthy")) -> Healthy | O2: 46128
A3: INV-CG-001-TRU-CND-002 | B3: CG-001 | C3: Gabriel Samra Coral Gables | D3: Truss | E3: TRU-CND-002 | F3: Infusion Conditioner | G3: Hair Care | H3: 29 | I3: 19 | J3: =SUMIFS(Sales_Transactions!$J:$J,Sales_Transactions!$C:$C,B3,Sales_Transactions!$F:$F,E3) -> 10 | K3: =H3+I3-J3 -> 38 | L3: 8 | M3: 20 | N3: =IF(K3<=L3,"Reorder Needed",IF(K3<=L3*1.5,"Watch","Healthy")) -> Healthy | O3: 46121
A4: INV-CG-001-TRU-MSK-003 | B4: CG-001 | C4: Gabriel Samra Coral Gables | D4: Truss | E4: TRU-MSK-003 | F4: Net Mask | G4: Treatment | H4: 16 | I4: 29 | J4: =SUMIFS(Sales_Transactions!$J:$J,Sales_Transactions!$C:$C,B4,Sales_Transactions!$F:$F,E4) -> 7 | K4: =H4+I4-J4 -> 38 | L4: 8 | M4: 20 | N4: =IF(K4<=L4,"Reorder Needed",IF(K4<=L4*1.5,"Watch","Healthy")) -> Healthy | O4: 46146
A5: INV-CG-001-TRU-OIL-004 | B5: CG-001 | C5: Gabriel Samra Coral Gables | D5: Truss | E5: TRU-OIL-004 | F5: Deluxe Prime Oil | G5: Finishing | H5: 21 | I5: 18 | J5: =SUMIFS(Sales_Transactions!$J:$J,Sales_Transactions!$C:$C,B5,Sales_Transactions!$F:$F,E5) -> 10 | K5: =H5+I5-J5 -> 29 | L5: 8 | M5: 20 | N5: =IF(K5<=L5,"Reorder Needed",IF(K5<=L5*1.5,"Watch","Healthy")) -> Healthy | O5: 46032
A6: INV-CG-001-TRU-SER-005 | B6: CG-001 | C6: Gabriel Samra Coral Gables | D6: Truss | E6: TRU-SER-005 | F6: Night Spa Serum | G6: Treatment | H6: 31 | I6: 26 | J6: =SUMIFS(Sales_Transactions!$J:$J,Sales_Transactions!$C:$C,B6,Sales_Transactions!$F:$F,E6) -> 7 | K6: =H6+I6-J6 -> 50 | L6: 8 | M6: 20 | N6: =IF(K6<=L6,"Reorder Needed",IF(K6<=L6*1.5,"Watch","Healthy")) -> Healthy | O6: 46158
A7: INV-CG-001-SUT-FIR-001 | B7: CG-001 | C7: Gabriel Samra Coral Gables | D7: Sutra | E7: SUT-FIR-001 | F7: Mini Flat Iron | G7: Hot Tools | H7: 11 | I7: 6 | J7: =SUMIFS(Sales_Transactions!$J:$J,Sales_Transactions!$C:$C,B7,Sales_Transactions!$F:$F,E7) -> 10 | K7: =H7+I7-J7 -> 7 | L7: 3 | M7: 6 | N7: =IF(K7<=L7,"Reorder Needed",IF(K7<=L7*1.5,"Watch","Healthy")) -> Healthy | O7: 46030
A8: INV-CG-001-SUT-CUR-002 | B8: CG-001 | C8: Gabriel Samra Coral Gables | D8: Sutra | E8: SUT-CUR-002 | F8: Clipless Curling Iron | G8: Hot Tools | H8: 9 | I8: 2 | J8: =SUMIFS(Sales_Transactions!$J:$J,Sales_Transactions!$C:$C,B8,Sales_Transactions!$F:$F,E8) -> 4 | K8: =H8+I8-J8 -> 7 | L8: 3 | M8: 6 | N8: =IF(K8<=L8,"Reorder Needed",IF(K8<=L8*1.5,"Watch","Healthy")) -> Healthy | O8: 46029
A9: INV-CG-001-SUT-BLO-003 | B9: CG-001 | C9: Gabriel Samra Coral Gables | D9: Sutra | E9: SUT-BLO-003 | F9: Blowout Brush | G9: Hot Tools | H9: 7 | I9: 5 | J9: =SUMIFS(Sales_Transactions!$J:$J,Sales_Transactions!$C:$C,B9,Sales_Transactions!$F:$F,E9) -> 7 | K9: =H9+I9-J9 -> 5 | L9: 3 | M9: 6 | N9: =IF(K9<=L9,"Reorder Needed",IF(K9<=L9*1.5,"Watch","Healthy")) -> Healthy | O9: 46062
A10: INV-CG-001-SUT-DRY-004 | B10: CG-001 | C10: Gabriel Samra Coral Gables | D10: Sutra | E10: SUT-DRY-004 | F10: Professional Hair Dryer | G10: Hot Tools | H10: 7 | I10: 7 | J10: =SUMIFS(Sales_Transactions!$J:$J,Sales_Transactions!$C:$C,B10,Sales_Transactions!$F:$F,E10) -> 12 | K10: =H10+I10-J10 -> 2 | L10: 3 | M10: 6 | N10: =IF(K10<=L10,"Reorder Needed",IF(K10<=L10*1.5,"Watch","Healthy")) -> Reorder Needed | O10: 46023
A11: INV-CG-001-SUT-HSP-005 | B11: CG-001 | C11: Gabriel Samra Coral Gables | D11: Sutra | E11: SUT-HSP-005 | F11: Heat Spray | G11: Styling | H11: 10 | I11: 8 | J11: =SUMIFS(Sales_Transactions!$J:$J,Sales_Transactions!$C:$C,B11,Sales_Transactions!$F:$F,E11) -> 8 | K11: =H11+I11-J11 -> 10 | L11: 3 | M11: 6 | N11: =IF(K11<=L11,"Reorder Needed",IF(K11<=L11*1.5,"Watch","Healthy")) -> Healthy | O11: 46058
A12: INV-DR-001-TRU-SHP-001 | B12: DR-001 | C12: Gabriel Samra Doral | D12: Truss | E12: TRU-SHP-001 | F12: Infusion Shampoo | G12: Hair Care | H12: 22 | I12: 22 | J12: =SUMIFS(Sales_Transactions!$J:$J,Sales_Transactions!$C:$C,B12,Sales_Transactions!$F:$F,E12) -> 4 | K12: =H12+I12-J12 -> 40 | L12: 8 | M12: 20 | N12: =IF(K12<=L12,"Reorder Needed",IF(K12<=L12*1.5,"Watch","Healthy")) -> Healthy | O12: 46070
A13: INV-DR-001-TRU-CND-002 | B13: DR-001 | C13: Gabriel Samra Doral | D13: Truss | E13: TRU-CND-002 | F13: Infusion Conditioner | G13: Hair Care | H13: 27 | I13: 26 | J13: =SUMIFS(Sales_Transactions!$J:$J,Sales_Transactions!$C:$C,B13,Sales_Transactions!$F:$F,E13) -> 13 | K13: =H13+I13-J13 -> 40 | L13: 8 | M13: 20 | N13: =IF(K13<=L13,"Reorder Needed",IF(K13<=L13*1.5,"Watch","Healthy")) -> Healthy | O13: 46084
... A21: INV-DR-001-SUT-HSP-005 | B21: DR-001 | C21: Gabriel Samra Doral | D21: Sutra | E21: SUT-HSP-005 | F21: Heat Spray | G21: Styling | H21: 9 | I21: 10 | J21: =SUMIFS(Sales_Transactions!$J:$J,Sales_Transactions!$C:$C,B21,Sales_Transactions!$F:$F,E21) -> 12 | K21: =H21+I21-J21 -> 7 | L21: 3 | M21: 6 | N21: =IF(K21<=L21,"Reorder Needed",IF(K21<=L21*1.5,"Watch","Healthy")) -> Healthy | O21: 46035

Sheet Stores
A1: Store_ID | B1: Salon_Location | C1: City | D1: Channel | E1: Manager | F1: Notes
A2: CG-001 | B2: Gabriel Samra Coral Gables | C2: Coral Gables | D2: In-Salon Retail | E2: Salon Manager | F2: Retail sales at front desk and stylist recommendation
A3: DR-001 | B3: Gabriel Samra Doral | C3: Doral | D3: In-Salon Retail | E3: Salon Manager | F3: Retail sales at front desk and stylist recommendation

Sheet Assumptions
A1: Field | B1: Description
A2: Purpose | B2: Mock raw data to simulate Gabriel Samra in-salon retail sales for Sutra and Truss products.
A3: Locations Included | B3: Coral Gables and Doral only. No online sales included.
A4: Use Case | B4: Streamlit can read these tabs to calculate sales, margin, inventory risk, product performance, and reorder alerts.
A5: Data Status | B5: Fictitious sample data until real POS / inventory exports are provided.
A6: Manual Inputs | B6: Unit cost, retail price, opening stock, received units, reorder point, and recommended reorder quantity are assumed.
A7: API/External Data | B7: No live API data is included in this file. It is structured to be replaced later by real exports.
